fancy_dataclass/__init__.py
fancy_dataclass/cli.py
fancy_dataclass/config.py
fancy_dataclass/dict.py
fancy_dataclass/func.py
fancy_dataclass/json.py
fancy_dataclass/mixin.py
fancy_dataclass/py.typed
fancy_dataclass/serialize.py
fancy_dataclass/settings.py
fancy_dataclass/sql.py
fancy_dataclass/subprocess.py
fancy_dataclass/toml.py
fancy_dataclass/utils.py
fancy_dataclass/versioned.py
fancy_dataclass-0.9.0.dist-info/METADATA
fancy_dataclass-0.9.0.dist-info/WHEEL
fancy_dataclass-0.9.0.dist-info/RECORD
