Metadata-Version: 2.3
Name: fancy-dataclass
Version: 0.9.0
Summary: Spiff up your dataclasses with extra features.
Project-URL: Documentation, https://fancy-dataclass.readthedocs.io
Project-URL: Issues, https://github.com/jeremander/fancy-dataclass/issues
Project-URL: Source, https://github.com/jeremander/fancy-dataclass
Project-URL: Changelog, https://fancy-dataclass.readthedocs.io/en/stable/CHANGELOG
Author-email: Jeremy Silver <jeremys@nessiness.com>
License: MIT License
Keywords: cli,config,dataclass,json,orm,serialize,toml
Classifier: Programming Language :: Python
Requires-Python: >=3.8
Requires-Dist: sqlalchemy>=2.0
Requires-Dist: tomlkit>=0.13.2
Requires-Dist: typing-extensions>=4.13
